ustubby/__init__.py
ustubby-0.1.1.dist-info/LICENSE
ustubby-0.1.1.dist-info/LICENSE.txt
ustubby-0.1.1.dist-info/METADATA
ustubby-0.1.1.dist-info/WHEEL
ustubby-0.1.1.dist-info/top_level.txt
ustubby-0.1.1.dist-info/RECORD
