Metadata-Version: 2.1
Name: ustubby
Version: 0.1.1
Summary: Micropython c stub generator
Home-page: https://github.com/pazzarpj/micropython-ustubby
Author: Ryan Parry-Jones
Author-email: ryanspj+github@gmail.com
License: UNKNOWN
Platform: UNKNOWN
Classifier: Development Status :: 4 - Beta
Classifier: Intended Audience :: Manufacturing
Classifier: License :: OSI Approved :: MIT License
Classifier: Programming Language :: Python :: 3 :: Only
Classifier: Programming Language :: Python :: 3.6
Classifier: Programming Language :: Python :: 3.7
Classifier: Programming Language :: Python :: 3.8
Requires-Python: >=3.6
